{"name":"Autenticación fallida de usuario con credito activo","id":"yo-como-usuario-de-rapicredit;autenticación-fallida-de-usuario-con-credito-activo","testSteps":[{"number":1,"description":"Dado que el usuario se encuentra en el login unificado de rapicredit","duration":8841,"startTime":"2024-02-05T15:38:07.829-05:00[America/Bogota]","screenshots":[{"screenshot":"6ff5e5d58c27ac84936be9ac64597ff072ee2fda9a0eb52531a1f08f1cf377c4.png","timeStamp":1707165496670}],"result":"SUCCESS","precondition":false,"level":0,"children":[{"number":2,"description":"User abrir pagina web","duration":5904,"startTime":"2024-02-05T15:38:09.846-05:00[America/Bogota]","screenshots":[{"screenshot":"427e5674ddfa5114785641da2a505dc7ffecb11de90a15fce98ffe699ea596cc.png","timeStamp":1707165490413},{"screenshot":"6ff5e5d58c27ac84936be9ac64597ff072ee2fda9a0eb52531a1f08f1cf377c4.png","timeStamp":1707165495750}],"result":"SUCCESS","precondition":false,"level":1,"children":[{"number":3,"description":"User opens the En la pagina web","duration":5297,"startTime":"2024-02-05T15:38:10.419-05:00[America/Bogota]","screenshots":[{"screenshot":"427e5674ddfa5114785641da2a505dc7ffecb11de90a15fce98ffe699ea596cc.png","timeStamp":1707165490440},{"screenshot":"6ff5e5d58c27ac84936be9ac64597ff072ee2fda9a0eb52531a1f08f1cf377c4.png","timeStamp":1707165495716}],"result":"SUCCESS","precondition":false,"level":2}]}]},{"number":4,"description":"Cuando ingresa las credenciales erroneamente","duration":23144,"startTime":"2024-02-05T15:38:16.674-05:00[America/Bogota]","screenshots":[{"screenshot":"af7a188ffca3451b6e00328cb665926713e8b0a336f82e49422c3af46b546d4b.png","timeStamp":1707165519818}],"result":"SUCCESS","precondition":false,"level":0,"children":[{"number":5,"description":"User navegar hacia el login","duration":18583,"startTime":"2024-02-05T15:38:16.706-05:00[America/Bogota]","screenshots":[{"screenshot":"aa6edf30ab35b4f1ba8ad763d32059463af1423fe1009744dc9513f00a94bc93.png","timeStamp":1707165497687},{"screenshot":"11b6b5351f0ab182388a0c76e316cb103d8c3fe55f536ff82a7331470c3061b7.png","timeStamp":1707165515289}],"result":"SUCCESS","precondition":false,"level":1,"children":[{"number":6,"description":"User clicks on login","duration":17398,"startTime":"2024-02-05T15:38:17.879-05:00[America/Bogota]","screenshots":[{"screenshot":"3b8ba1be320a1f516937bddcf7ed04e826d9cf47a591734bbc558523b2ad649c.png","timeStamp":1707165498867},{"screenshot":"11b6b5351f0ab182388a0c76e316cb103d8c3fe55f536ff82a7331470c3061b7.png","timeStamp":1707165515277}],"result":"SUCCESS","precondition":false,"level":2}]},{"number":7,"description":"User diligenciar login","duration":4515,"startTime":"2024-02-05T15:38:35.290-05:00[America/Bogota]","screenshots":[{"screenshot":"11b6b5351f0ab182388a0c76e316cb103d8c3fe55f536ff82a7331470c3061b7.png","timeStamp":1707165515299},{"screenshot":"af7a188ffca3451b6e00328cb665926713e8b0a336f82e49422c3af46b546d4b.png","timeStamp":1707165519805}],"result":"SUCCESS","precondition":false,"level":1,"children":[{"number":8,"description":"User enters \u0027correodeprueba40@yopmail.com\u0027 into Correo","duration":1447,"startTime":"2024-02-05T15:38:35.417-05:00[America/Bogota]","screenshots":[{"screenshot":"11b6b5351f0ab182388a0c76e316cb103d8c3fe55f536ff82a7331470c3061b7.png","timeStamp":1707165515774},{"screenshot":"b3c513744e33191ef5aff07d6b6b5ee123b2a8f606f3d3df822dbd1aa6e393a1.png","timeStamp":1707165516864}],"result":"SUCCESS","precondition":false,"level":2},{"number":9,"description":"User enters \u0027123456\u0027 into Contraseña","duration":1418,"startTime":"2024-02-05T15:38:36.980-05:00[America/Bogota]","screenshots":[{"screenshot":"cd5d07899ef5eb4a3e114838e45573988620d240717293e7f34b437260b1602a.png","timeStamp":1707165517322},{"screenshot":"748827d8465a16447fb307b115e6897eae6e421ec5fb27312043c0869297f983.png","timeStamp":1707165518398}],"result":"SUCCESS","precondition":false,"level":2},{"number":10,"description":"User clicks on Ingresar","duration":1262,"startTime":"2024-02-05T15:38:38.532-05:00[America/Bogota]","screenshots":[{"screenshot":"748827d8465a16447fb307b115e6897eae6e421ec5fb27312043c0869297f983.png","timeStamp":1707165518893},{"screenshot":"af7a188ffca3451b6e00328cb665926713e8b0a336f82e49422c3af46b546d4b.png","timeStamp":1707165519794}],"result":"SUCCESS","precondition":false,"level":2}]}]},{"number":11,"description":"Entonces el usuario No debe poder autenticarse","duration":1258,"startTime":"2024-02-05T15:38:39.818-05:00[America/Bogota]","screenshots":[{"screenshot":"77391da92d9c6456b7299dd67e8376dabc74716df25d5d4b5851a10210e0887a.png","timeStamp":1707165521074}],"result":"SUCCESS","precondition":false,"level":0,"children":[{"number":12,"description":"Then login fallido should be (true)","duration":1229,"startTime":"2024-02-05T15:38:39.832-05:00[America/Bogota]","screenshots":[{"screenshot":"77391da92d9c6456b7299dd67e8376dabc74716df25d5d4b5851a10210e0887a.png","timeStamp":1707165521061}],"result":"SUCCESS","precondition":false,"level":1}]}],"userStory":{"id":"yo-como-usuario-de-rapicredit","storyName":"Yo como usuario de rapicredit","path":"file:///C:/Users/robert.aroca/IdeaProjects/co.com.Rapicredit/src/test/resources/features/login/login.feature","narrative":"  Quiero hacer login en la plataforma de rapiplazo\n  Para ver la información de mi credito","type":"feature"},"featureTag":{"name":"Login/Yo como usuario de rapicredit","type":"feature","displayName":"Login/Yo como usuario de rapicredit"},"title":"Autenticación fallida de usuario con credito activo","tags":[{"name":"Crear cuenta rapiplazo","type":"capability","displayName":"Crear cuenta rapiplazo"},{"name":"Crear cuenta rapiplazo/Yo como usuario de rapicredit","type":"feature","displayName":"Yo como usuario de rapicredit"}],"startTime":"2024-02-05T15:38:07.826-05:00[America/Bogota]","duration":33251,"projectKey":"","sessionId":"47bff2e81ef734e93247995b8825dfa9","driver":"chrome","isManualTestingUpToDate":false,"manual":false,"testSource":"Cucumber","actors":[{"name":"User","can":["browse the web"]}],"result":"SUCCESS"}